Workbook

Sheet Backlog
A1: Release | B1: Épica | C1: Nombre de épica | D1: ID | E1: Historia | F1: SP | G1: Criterio de aceptación | H1: Traza RN / INV | I1: Depende de | J1: Generación IA | K1: Prioridad
A2: R0 Fundación | B2: E01 | C2: Plataforma y entornos | D2: US-001 | E2: Monorepo, CI y verificación estática | F2: 5 | G2: El pipeline compila backend y frontend; LINT-003/004/005 bloquean la fusión; el esquema se ejecuta con cero errores en cada integración | H2: BR-05, BR-08 | I2: — | J2: Permitida | K2: Crítica
A3: R0 Fundación | B3: E01 | C3: Plataforma y entornos | D3: US-002 | E3: Entornos dev, staging y producción con gestión de secretos | F3: 8 | G3: Tres entornos aislados; ningún secreto en repositorio; rotación documentada | H3: RN-223 | I3: US-001 | J3: Permitida | K3: Crítica
A4: R0 Fundación | B4: E01 | C4: Plataforma y entornos | D4: US-003 | E4: Datos semilla anonimizados para entornos no productivos | F4: 5 | G4: Ningún entorno distinto de producción contiene datos personales reales | H4: RN-223 | I4: US-002 | J4: Permitida | K4: Alta
A5: R0 Fundación | B5: E01 | C5: Plataforma y entornos | D5: US-004 | E5: Presupuesto de rendimiento y matriz de compatibilidad en CI | F5: 3 | G5: Falla la integración si LCP supera 2,5 s o el bundle inicial supera 200 KB | H5: RN-211, RN-212 | I5: US-001 | J5: Permitida | K5: Alta
A6: R0 Fundación | B6: E02 | C6: Esquema y migraciones | D6: US-005 | E6: Migraciones 001 a 013: dominios, roles, mercado, identidad, cliente, sorteo, premio, registrables, orden, pago, ticket, sorteo ejecutado, resolución | F6: 8 | G6: Se ejecutan en orden con cero errores; los roles existen antes de las revocaciones | H6: RN-219 a RN-222 | I6: US-001 | J6: Permitida | K6: Crítica
A7: R0 Fundación | B7: E02 | C7: Esquema y migraciones | D7: US-006 | E7: Migraciones 014 a 026: controversias, contabilidad, liquidación, saldo, cumplimiento, protección, analítica, alarmas, auditoría, growth, acceso, particiones, semilla | F7: 5 | G7: 114 tablas creadas; 8 tipos de sorteo sembrados; cuentas contables por moneda | H7: RN-219, RN-14-bis | I7: US-005 | J7: Permitida | K7: Crítica
A8: R0 Fundación | B8: E02 | C8: Esquema y migraciones | D8: US-007 | E8: Particionamiento y job de creación anticipada | F8: 5 | G8: Particiones del mes siguiente creadas con 30 días de antelación; su ausencia genera alarma alta | H8: RN-222 | I8: US-006 | J8: Permitida | K8: Alta
A9: R0 Fundación | B9: E03 | C9: Identidad y autenticación | D9: US-008 | E9: Registro con unicidad de documento, correo y teléfono | F9: 5 | G9: Un documento corresponde a un solo usuario activo; el intento duplicado genera evento de riesgo | H9: INV-08, RN-115 | I9: US-006 | J9: Permitida | K9: Crítica
A10: R0 Fundación | B10: E03 | C10: Identidad y autenticación | D10: US-009 | E10: Verificación de contacto y declaración de edad | F10: 3 | G10: Registro rechazado si es menor; documento bloqueado permanentemente | H10: RN-119 | I10: US-008 | J10: Permitida | K10: Crítica
A11: R0 Fundación | B11: E03 | C11: Identidad y autenticación | D11: US-010 | E11: Autenticación con testigo portable y renovación rotatoria | F11: 5 | G11: Nunca solo por cookie; la reutilización revoca la familia y genera evento de riesgo | H11: RN-213 | I11: US-008 | J11: Permitida | K11: Crítica
A12: R0 Fundación | B12: E03 | C12: Identidad y autenticación | D12: US-011 | E12: Verificación de identidad con prueba de vida antes de la primera compra | F12: 5 | G12: Sin verificación no hay compra; la navegación no se bloquea | H12: RN-116, RN-117, RN-003 | I12: US-010 | J12: Permitida | K12: Crítica
A13: R0 Fundación | B13: E03 | C13: Identidad y autenticación | D13: US-012 | E13: Vigencia documental con aviso y bloqueo parcial | F13: 3 | G13: Aviso a 30 días; con documento vencido puede reclamar premios y usar saldo, no comprar | H13: RN-124, RN-125 | I13: US-011 | J13: Permitida | K13: Alta
... A137: R6 Crecimiento y lanzamiento | B137: E39 | C137: LIBOX Club | D137: US-136 | E137: Criterio doble de encendido de LIBOX Club | F137: 2 | G137: Aliados con beneficio activo y volumen de verificados. Ninguno se salta | H137: RN-194-undecies | I137: US-134 | J137: Permitida | K137: Media

Sheet Resumen
A1: LIBOX Backlog MVP V3 — Resumen de planificación
A3: Parámetro | B3: Valor
A4: Equipo (personas) | B4: 4
A5: Velocidad por sprint (SP) | B5: 32
A6: Duración de sprint (semanas) | B6: 2
A7: Total SP del backlog | B7: =SUM(Backlog!F2:F137) -> 936
A8: Total historias | B8: =COUNTA(Backlog!D2:D137) -> 136
A9: Sprints necesarios | B9: =ROUNDUP(B7/B5,0) -> 30
A10: Semanas | B10: =B9*B6 -> 60
A11: Meses aproximados | B11: =ROUND(B9*B6/4.33,1) -> 13.9
A13: Entrega | B13: SP | C13: Historias | D13: % del total
A14: R0 Fundación | B14: =SUMIF(Backlog!$A$2:$A$137,A14,Backlog!$F$2:$F$137) -> 102 | C14: =COUNTIF(Backlog!$A$2:$A$137,A14) -> 20 | D14: =B14/$B$7 -> 0.10897436
A15: R1 Núcleo transaccional | B15: =SUMIF(Backlog!$A$2:$A$137,A15,Backlog!$F$2:$F$137) -> 243 | C15: =COUNTIF(Backlog!$A$2:$A$137,A15) -> 34 | D15: =B15/$B$7 -> 0.25961538
A16: R2 Confianza y resolución | B16: =SUMIF(Backlog!$A$2:$A$137,A16,Backlog!$F$2:$F$137) -> 131 | C16: =COUNTIF(Backlog!$A$2:$A$137,A16) -> 19 | D16: =B16/$B$7 -> 0.13995726
A17: R3 Cumplimiento y protección | B17: =SUMIF(Backlog!$A$2:$A$137,A17,Backlog!$F$2:$F$137) -> 102 | C17: =COUNTIF(Backlog!$A$2:$A$137,A17) -> 16 | D17: =B17/$B$7 -> 0.10897436
A18: R4 Catálogo ampliado | B18: =SUMIF(Backlog!$A$2:$A$137,A18,Backlog!$F$2:$F$137) -> 97 | C18: =COUNTIF(Backlog!$A$2:$A$137,A18) -> 11 | D18: =B18/$B$7 -> 0.10363248
A19: R5 Plataforma y regímenes | B19: =SUMIF(Backlog!$A$2:$A$137,A19,Backlog!$F$2:$F$137) -> 136 | C19: =COUNTIF(Backlog!$A$2:$A$137,A19) -> 17 | D19: =B19/$B$7 -> 0.14529915
A20: R6 Crecimiento y lanzamiento | B20: =SUMIF(Backlog!$A$2:$A$137,A20,Backlog!$F$2:$F$137) -> 125 | C20: =COUNTIF(Backlog!$A$2:$A$137,A20) -> 19 | D20: =B20/$B$7 -> 0.13354701
A21: Total | B21: =SUM(B14:B20) -> 936 | C21: =SUM(C14:C20) -> 136
A23: SP con generación de IA prohibida | B23: =SUMIF(Backlog!$J$2:$J$137,"*Prohibida*",Backlog!$F$2:$F$137) -> 261
A24: SP de prioridad crítica | B24: =SUMIF(Backlog!$K$2:$K$137,"Crítica",Backlog!$F$2:$F$137) -> 478

Sheet Notas
A1: Campo | B1: Significado
A2: Generación IA — Prohibida | B2: Zona crítica de L4/L3: se escribe a mano y se revisa por segunda persona. Propiedad fija, no rotatoria.
A3: Traza RN / INV | B3: Regla de negocio del PRD MVP V3 o invariante verificable por prueba automatizada. Sin traza la historia no entra al sprint.
A4: SP | B4: Estimación con factor de asistencia de IA ya aplicado por bloque. Ver Backlog V2 §1.2.
A5: Velocidad 32 SP | B5: 4 personas generalistas, sprint de 2 semanas. Valor de entrada, editable en azul.
A6: Gate R1 | B6: Ensayo en entorno controlado. Valida la lógica, no la realidad: el contracargo no puede simularse.
A7: Gate R5 | B7: Ensayo con dinero real. Innegociable antes de que un usuario del público pague.
A8: Encendido progresivo | B8: Todo tipo y categoría se construye habilitado en el modelo y apagado por configuración.
